onePerceptron/__init__.py
onePerceptron/perceptron.py
onePerceptron_pkg-0.0.2.dist-info/LICENSE
onePerceptron_pkg-0.0.2.dist-info/METADATA
onePerceptron_pkg-0.0.2.dist-info/WHEEL
onePerceptron_pkg-0.0.2.dist-info/top_level.txt
onePerceptron_pkg-0.0.2.dist-info/RECORD
