Metadata-Version: 2.1
Name: onePerceptron-pkg
Version: 0.0.2
Summary: A small package for perceptron
Home-page: https://github.com/iambalakrishnan/onePerceptron-pkg
Author: iambalakrishnan
Author-email: imbkrishnaa@gmail.com
Project-URL: Bug Tracker, https://github.com/iambalakrishnan/onePerceptron-pkg/issues
Classifier: Programming Language :: Python :: 3
Classifier: License :: OSI Approved :: MIT License
Classifier: Operating System :: OS Independent
Requires-Python: >=3.7
License-File: LICENSE
Requires-Dist: numpy (==1.21.4)
Requires-Dist: pandas (==1.3.4)
Requires-Dist: joblib (==1.1.0)
